assets/images/broadcast.png
assets/images/episode.png
assets/images/series.png
crodl/__init__.py
crodl/main.py
crodl/run.py
crodl/settings.py
crodl/exceptions/__init__.py
crodl/exceptions/exc.py
crodl/program/__init__.py
crodl/program/audiowork.py
crodl/program/content.py
crodl/program/series.py
crodl/program/show.py
crodl/streams/__init__.py
crodl/streams/audioparts.py
crodl/streams/dash.py
crodl/streams/download.py
crodl/streams/hls.py
crodl/streams/mp3.py
crodl/streams/utils.py
crodl/tools/__init__.py
crodl/tools/logger.py
crodl/tools/scrap.py
crodl/tools/timer.py
cro_dl-1.1.14.dist-info/METADATA
cro_dl-1.1.14.dist-info/WHEEL
cro_dl-1.1.14.dist-info/entry_points.txt
cro_dl-1.1.14.dist-info/top_level.txt
cro_dl-1.1.14.dist-info/RECORD
