Metadata-Version: 2.4
Name: cro-dl
Version: 1.1.14
Summary: Enjoy the ČRo offline
Author-email: Oldrich Klimanek <klimanek@scinet.cz>
License: BSD
Project-URL: Repository, https://github.com/klimanek/cro-dl
Project-URL: Issues, https://github.com/klimanek/cro-dl/issues
Requires-Python: <4.0,>=3.10
Requires-Dist: requests<3.0.0,>=2.31.0
Requires-Dist: aiohttp<4.0.0,>=3.9.4
Requires-Dist: icecream<3.0.0,>=2.1.3
Requires-Dist: beautifulsoup4<5.0.0,>=4.12.3
Requires-Dist: rich<14.0.0,>=13.8.1
Requires-Dist: lxml<6.0.0,>=5.3.0
Requires-Dist: yaspin<4.0.0,>=3.0.2
Requires-Dist: asyncclick<9.0.0.0,>=8.1.7.2
